synthea_pydantic/__init__.py
synthea_pydantic/_parsers.py
synthea_pydantic/allergies.py
synthea_pydantic/base.py
synthea_pydantic/careplans.py
synthea_pydantic/claims.py
synthea_pydantic/claims_transactions.py
synthea_pydantic/conditions.py
synthea_pydantic/devices.py
synthea_pydantic/encounters.py
synthea_pydantic/imaging_studies.py
synthea_pydantic/immunizations.py
synthea_pydantic/medications.py
synthea_pydantic/observations.py
synthea_pydantic/organizations.py
synthea_pydantic/patients.py
synthea_pydantic/payer_transitions.py
synthea_pydantic/payers.py
synthea_pydantic/procedures.py
synthea_pydantic/providers.py
synthea_pydantic/supplies.py
synthea_pydantic-0.1.0.dist-info/licenses/LICENSE
synthea_pydantic-0.1.0.dist-info/METADATA
synthea_pydantic-0.1.0.dist-info/WHEEL
synthea_pydantic-0.1.0.dist-info/top_level.txt
synthea_pydantic-0.1.0.dist-info/RECORD
