Metadata-Version: 2.4
Name: synthea-pydantic
Version: 0.1.0
Summary: Type-safe Pydantic models for Synthea health data CSV exports
License: MIT
Keywords: synthea,healthcare,pydantic,csv,synthetic-data,health-data
Classifier: Development Status :: 4 - Beta
Classifier: Intended Audience :: Developers
Classifier: Intended Audience :: Healthcare Industry
Classifier: Intended Audience :: Science/Research
Classifier: License :: OSI Approved :: MIT License
Classifier: Operating System :: OS Independent
Classifier: Programming Language :: Python :: 3
Classifier: Programming Language :: Python :: 3.12
Classifier: Programming Language :: Python :: 3.13
Classifier: Topic :: Scientific/Engineering :: Medical Science Apps.
Classifier: Topic :: Software Development :: Libraries :: Python Modules
Classifier: Typing :: Typed
Requires-Python: >=3.12
License-File: LICENSE
Requires-Dist: pydantic>=2.0
Dynamic: license-file
